[ {
  "images" : [ ],
  "isPerfect" : true,
  "UPC" : "",
  "SN" : "ggggg",
  "SKU" : "frakhat shiza",
  "PN" : ""
}, {
  "images" : [ ],
  "isPerfect" : true,
  "UPC" : "d",
  "SN" : "ауа",
  "SKU" : "уукц",
  "PN" : ""
}, {
  "images" : [ ],
  "isPerfect" : true,
  "UPC" : "545h4",
  "SN" : "hg",
  "SKU" : "hg",
  "PN" : "yhterr"
}, {
  "images" : [ ],
  "isPerfect" : true,
  "UPC" : "12348",
  "SN" : "12346",
  "SKU" : "12345",
  "PN" : "12347"
}, {
  "images" : [ ],
  "isPerfect" : true,
  "UPC" : "13456648",
  "SN" : "12345666",
  "SKU" : "13456645",
  "PN" : "12345667"
} ]